envveil/__init__.py
envveil/cli.py
envveil/encryptor.py
envveil/patterns.py
envveil/scanner.py
envveil/secret_patterns.txt
envveil-0.3.1.dist-info/licenses/LICENSE
envveil-0.3.1.dist-info/METADATA
envveil-0.3.1.dist-info/WHEEL
envveil-0.3.1.dist-info/entry_points.txt
envveil-0.3.1.dist-info/top_level.txt
envveil-0.3.1.dist-info/RECORD
