Metadata-Version: 2.4
Name: envveil
Version: 0.3.1
Summary: Scan, encrypt, and manage secrets in your project with key file or passphrase-based encryption.
Author-email: Satarupa Deb <satarupa2212@gmail.com>
License: MIT
Project-URL: Homepage, https://github.com/yourusername/envveil
Requires-Python: >=3.7
License-File: LICENSE
Requires-Dist: cryptography>=41.0.0
Requires-Dist: requests>=2.0.0
Dynamic: license-file
